scarabaeus/__init__.py
Scarabaeus-0.0.1.dist-info/LICENSE
Scarabaeus-0.0.1.dist-info/METADATA
Scarabaeus-0.0.1.dist-info/WHEEL
Scarabaeus-0.0.1.dist-info/top_level.txt
Scarabaeus-0.0.1.dist-info/RECORD
