Metadata-Version: 2.1
Name: Scarabaeus
Version: 0.0.1
Summary: A simple way to manage plugins and events in Python
Author-email: Quik <quik@daskju.com>
License: Copyright © 2022 Daskju.com, The Daskju Project
Classifier: Programming Language :: Python :: 3
Classifier: License :: OSI Approved :: MIT License
Classifier: Operating System :: OS Independent
Requires-Python: >=3.6
License-File: LICENSE
